jpdemo/__init__.py
jpdemo/eventdemo1.py
jpwidgets/__init__.py
jpwidgets/version.py
jpwidgets/widgets.py
pyJustpyWidgets-0.0.2.dist-info/LICENSE
pyJustpyWidgets-0.0.2.dist-info/METADATA
pyJustpyWidgets-0.0.2.dist-info/WHEEL
pyJustpyWidgets-0.0.2.dist-info/top_level.txt
pyJustpyWidgets-0.0.2.dist-info/RECORD
