Metadata-Version: 2.1
Name: pyJustpyWidgets
Version: 0.0.2
Summary: justpy Widgets
Home-page: http://wiki.bitplan.com/index.php/pyJustpyWidgets
Author: Wolfgang Fahl
Author-email: wf@bitplan.com
License: Apache
Download-URL: https://github.com/WolfgangFahl/pyJustpyWidgets
Project-URL: Code, https://github.com/WolfgangFahl/pyJustpyWidgets
Project-URL: Issue tracker, https://github.com/WolfgangFahl/pyJustpyWidgets/issues
Platform: UNKNOWN
Classifier: Programming Language :: Python
Classifier: Programming Language :: Python :: 3.8
Classifier: Programming Language :: Python :: 3.9
Classifier: Programming Language :: Python :: 3.10
License-File: LICENSE
Requires-Dist: justpy (~=0.2.3)
